{
  "name": "Gene Santos",
  "age": 57,
  "address": {
    "street": "Iffol Trail",
    "city": "Adafuro",
    "state": "NH",
    "zip": "72807"
  },
  "contact": {
    "phone": "(326) 234-4395",
    "servicePhone": "800542278"
  },
  "birthday": "1972-11-13T14:38:59.720Z",
  "ip": "169.44.74.175",
  "foo": "bar",
  "profile": {
    "about": "Wiesate hobda ku pifru zilamu sihu wo higozot nollin sutgi sutekar feidlus ecawa. Bem tufzo wewe une wojaz sukiro asove ogetolac ihijedsik lebuve ulhop woic kobvihod wi fazre hubu. Vojigu juravwol hom ewtek tolkez ole boptihen tin ni pembeil piwasug icece.",
    "bio": "Fejuipe ine hergi najri ga tumicued bevad keze dajbuc feil ti ciwle ununo apudo ota ohe va cogizad. Ru lam uf tap okvuwu ajurug biruko ric wopaaba oleebiga hi fejir ar elorurpez da. Ufhukone ac atebo ufotur oza inowija mokarsep len ar mokpe hijelovo ozearooz eha. Femeh nobitemo cole nevlas pemeto ivarlig vozwe rojzute wa socic difa kuwi miurjac ovfomta pu emicutnes. Latcogaf pevku ezojezija piwdi zetfikpar ag tub vogmim alnuub facneopi nuftag ladmaname wipez."
  },
  "apiKey": "c0a2da2a93ccf1f8ff53aec9cbf0d1b604a99bdd7f3ee1304d93afe822a2c65a",
  "currency": {
    "code": "HTG",
    "name": "Haiti Gourde"
  }
}