{
  "name": "Addie Rhodes",
  "age": 34,
  "address": {
    "street": "Nehfik Drive",
    "city": "Fekagoco",
    "state": "TN",
    "zip": "36380"
  },
  "contact": {
    "phone": "(627) 797-2663",
    "servicePhone": "800428494"
  },
  "birthday": "2003-12-29T03:26:12.244Z",
  "ip": "240.38.125.22",
  "foo": "bar",
  "profile": {
    "about": "Mezeref uz coeske izole jammuk jiwpivoz iw ved sulurvah buw haic enurim reloroko beevawo ubuonijet. Rufeza bu eme kursiz gukar ussu afa cevtun izeemuot wasun vowiivi zouhrof. Hov toroh citejef gutzez focu us is hunuc ba zen hoiwmu aszat afuwet vazo ji odoc. Bueza coposa ta dujwezun ac uz hawekuraz ki cur wam dubop hukmebsa tis fav ujesuval hisoig datwiha rudzajra. Fijos vudi pos homu taef dehra vonozif aho momemej bizemedo uho viropmol bewpafevi ralu. Go suz haftelwi cidse awisavreg muigofu uvivipel talihdac nonjohi opive geljul mih saljof ragnokno kebek. Lilgika hezbafsi ituzuwef abivo osos metan dedmu lucuggo rofdep beni wuril vavoawa kucdu nilos zabej.",
    "bio": "Vabge civ ze safe hum afuzip jizde te ku muzfu losigpaj bope kibi ibuputli sijo. Setuh pahib nejijsid loj ikib juwike dubsagken zevik sitbuw nog fuv ozekiuso libuchot batuv duf ihool jizjaha pepebbuv. Moklo zienbu jumola gapa cigoha gedu veza fegfoc toune lepabrap nogkiwrij kuf rusomcej vimila nak no nid sa. Fu biz remmucma dutrewu erok hu mi ujoica tuke omage de nopvovbij jawviz va betru. Hob ca camiso etruftu ow emoowana gu wetno kevnegnel cojrafi pepompo wuvnarlod lubobo tapehih wi rag."
  },
  "apiKey": "eb1b369b2a4bd3794a152659ffa1cdc3be19755f3751ad4f6188431f76d4d91c",
  "currency": {
    "code": "NAD",
    "name": "Namibia Dollar"
  }
}